{
  "project_info": {
    "project_number": "398440786800",
    "project_id": "fluttercloudfunctions-6a3e3",
    "storage_bucket": "fluttercloudfunctions-6a3e3.appspot.com"
  },
  "client": [
    {
      "client_info": {
        "mobilesdk_app_id": "1:398440786800:android:49f948ee46632baddb3db5",
        "android_client_info": {
          "package_name": "com.example.flutter_cloud_functions"
        }
      },
      "oauth_client": [
        {
          "client_id": "398440786800-ce2o70uco38jhmhc9nfuree491mt5h8h.apps.googleusercontent.com",
          "client_type": 3
        }
      ],
      "api_key": [
        {
          "current_key": "AIzaSyCsKnJF1L_ip_-RmQoTvEObm0M3l0_uhFY"
        }
      ],
      "services": {
        "appinvite_service": {
          "other_platform_oauth_client": [
            {
              "client_id": "398440786800-ce2o70uco38jhmhc9nfuree491mt5h8h.apps.googleusercontent.com",
              "client_type": 3
            }
          ]
        }
      }
    }
  ],
  "configuration_version": "1"
}